xinaprocessor/__init__.py
xinaprocessor/base.py
xinaprocessor/classes.py
xinaprocessor/cleaners.py
xinaprocessor/constants.py
xinaprocessor/decorators.py
xinaprocessor/helper.py
xinaprocessor-0.41.dist-info/LICENSE
xinaprocessor-0.41.dist-info/METADATA
xinaprocessor-0.41.dist-info/WHEEL
xinaprocessor-0.41.dist-info/top_level.txt
xinaprocessor-0.41.dist-info/RECORD
