Metadata-Version: 2.1
Name: xinaprocessor
Version: 0.41
Summary: Xina processing library
Home-page: https://github.com/xina-ai/xinaprocessor
Author: Xina AI
License: UNKNOWN
Platform: UNKNOWN
Requires-Dist: emoji (==0.6.0)
Requires-Dist: tqdm (==4.55.0)
